{"nodes": [{"id": "website_public_components_ssr", "label": "ssr component (spark-ssr docs)", "file_type": "document", "source_file": "website/public/components/ssr.html", "source_location": null, "source_url": null, "captured_at": null, "author": null, "contributor": null}, {"id": "website_ssr_concept_template_is_schema", "label": "spark-ssr: template infers schema/REST/auth/hydration", "file_type": "concept", "source_file": "website/public/components/ssr.html", "source_location": null, "source_url": null, "captured_at": null, "author": null, "contributor": null, "rationale": "Every other full-stack framework asks you to describe the app twice (UI + models/resolvers); spark-ssr derives the rest from the one template you already wrote."}, {"id": "website_ssr_concept_data_sources", "label": "Four data-source shapes: SQL, URL fetch, markdown glob, JS module", "file_type": "concept", "source_file": "website/public/components/ssr.html", "source_location": null, "source_url": null, "captured_at": null, "author": null, "contributor": null}, {"id": "website_ssr_concept_pinterest_guide", "label": "Guide: Pinterest-style SQL-driven app (examples/pinterest)", "file_type": "concept", "source_file": "website/public/components/ssr.html", "source_location": null, "source_url": null, "captured_at": null, "author": null, "contributor": null}, {"id": "website_ssr_concept_tabtube_guide", "label": "Guide: TabTube module-source app (examples/tabtube)", "file_type": "concept", "source_file": "website/public/components/ssr.html", "source_location": null, "source_url": null, "captured_at": null, "author": null, "contributor": null}, {"id": "website_ssr_concept_auth_sessions", "label": "Built-in auth & HMAC-signed sessions", "file_type": "concept", "source_file": "website/public/components/ssr.html", "source_location": null, "source_url": null, "captured_at": null, "author": null, "contributor": null}, {"id": "website_ssr_concept_forms_no_js", "label": "Forms without JavaScript (server-side re-validation)", "file_type": "concept", "source_file": "website/public/components/ssr.html", "source_location": null, "source_url": null, "captured_at": null, "author": null, "contributor": null}, {"id": "website_ssr_concept_performance", "label": "spark-ssr performance: precompiled render programs, response cache, streaming, batched relations", "file_type": "concept", "source_file": "website/public/components/ssr.html", "source_location": null, "source_url": null, "captured_at": null, "author": null, "contributor": null}, {"id": "website_ssr_concept_security", "label": "spark-ssr security posture (SECURITY.md, test-pinned protections)", "file_type": "concept", "source_file": "website/public/components/ssr.html", "source_location": null, "source_url": null, "captured_at": null, "author": null, "contributor": null}], "edges": [{"source": "website_public_components_ssr", "target": "website_ssr_concept_template_is_schema", "relation": "conceptually_related_to", "confidence": "EXTRACTED", "confidence_score": 1.0, "source_file": "website/public/components/ssr.html", "source_location": null, "weight": 1.0}, {"source": "website_public_components_ssr", "target": "website_ssr_concept_data_sources", "relation": "conceptually_related_to", "confidence": "EXTRACTED", "confidence_score": 1.0, "source_file": "website/public/components/ssr.html", "source_location": null, "weight": 1.0}, {"source": "website_public_components_ssr", "target": "website_ssr_concept_pinterest_guide", "relation": "references", "confidence": "EXTRACTED", "confidence_score": 1.0, "source_file": "website/public/components/ssr.html", "source_location": null, "weight": 1.0}, {"source": "website_public_components_ssr", "target": "website_ssr_concept_tabtube_guide", "relation": "references", "confidence": "EXTRACTED", "confidence_score": 1.0, "source_file": "website/public/components/ssr.html", "source_location": null, "weight": 1.0}, {"source": "website_ssr_concept_pinterest_guide", "target": "website_ssr_concept_data_sources", "relation": "conceptually_related_to", "confidence": "EXTRACTED", "confidence_score": 1.0, "source_file": "website/public/components/ssr.html", "source_location": null, "weight": 1.0}, {"source": "website_ssr_concept_tabtube_guide", "target": "website_ssr_concept_data_sources", "relation": "conceptually_related_to", "confidence": "EXTRACTED", "confidence_score": 1.0, "source_file": "website/public/components/ssr.html", "source_location": null, "weight": 1.0}, {"source": "website_ssr_concept_pinterest_guide", "target": "website_ssr_concept_auth_sessions", "relation": "conceptually_related_to", "confidence": "EXTRACTED", "confidence_score": 1.0, "source_file": "website/public/components/ssr.html", "source_location": null, "weight": 1.0}, {"source": "website_ssr_concept_pinterest_guide", "target": "website_ssr_concept_forms_no_js", "relation": "conceptually_related_to", "confidence": "EXTRACTED", "confidence_score": 1.0, "source_file": "website/public/components/ssr.html", "source_location": null, "weight": 1.0}, {"source": "website_public_components_ssr", "target": "website_ssr_concept_auth_sessions", "relation": "conceptually_related_to", "confidence": "EXTRACTED", "confidence_score": 1.0, "source_file": "website/public/components/ssr.html", "source_location": null, "weight": 1.0}, {"source": "website_public_components_ssr", "target": "website_ssr_concept_forms_no_js", "relation": "conceptually_related_to", "confidence": "EXTRACTED", "confidence_score": 1.0, "source_file": "website/public/components/ssr.html", "source_location": null, "weight": 1.0}, {"source": "website_public_components_ssr", "target": "website_ssr_concept_performance", "relation": "conceptually_related_to", "confidence": "EXTRACTED", "confidence_score": 1.0, "source_file": "website/public/components/ssr.html", "source_location": null, "weight": 1.0}, {"source": "website_public_components_ssr", "target": "website_ssr_concept_security", "relation": "conceptually_related_to", "confidence": "EXTRACTED", "confidence_score": 1.0, "source_file": "website/public/components/ssr.html", "source_location": null, "weight": 1.0}, {"source": "website_public_components_ssr", "target": "website_concept_ambient_helpers", "relation": "conceptually_related_to", "confidence": "EXTRACTED", "confidence_score": 1.0, "source_file": "website/public/components/ssr.html", "source_location": null, "weight": 1.0}, {"source": "website_public_components_ssr", "target": "website_concept_navigate_helper", "relation": "conceptually_related_to", "confidence": "EXTRACTED", "confidence_score": 1.0, "source_file": "website/public/components/ssr.html", "source_location": null, "weight": 1.0}], "hyperedges": [{"id": "hyperedge_ssr_data_source_guides", "label": "spark-ssr data-source shapes exemplified by guides", "nodes": ["website_ssr_concept_data_sources", "website_ssr_concept_pinterest_guide", "website_ssr_concept_tabtube_guide"], "relation": "participate_in", "confidence": "EXTRACTED", "confidence_score": 1.0, "source_file": "website/public/components/ssr.html"}]}